proxy_manager_g4/__init__.py
proxy_manager_g4/consts.py
proxy_manager_g4/proxy.py
proxy_manager_g4-1.1.0.dist-info/LICENSE
proxy_manager_g4-1.1.0.dist-info/METADATA
proxy_manager_g4-1.1.0.dist-info/WHEEL
proxy_manager_g4-1.1.0.dist-info/top_level.txt
proxy_manager_g4-1.1.0.dist-info/RECORD
