Metadata-Version: 2.1
Name: proxy-manager-g4
Version: 1.1.0
Summary: Proxy Manager
Home-page: https://github.com/Genzo4/proxy_manager
Author: Genzo
Author-email: genzo@bk.ru
License: MIT
Project-URL: Bug Tracker, https://github.com/Genzo4/proxy_manager/issues
Keywords: proxy,proxy_manager,manager,proxy-manager,proxymanager,g4
Classifier: Development Status :: 4 - Beta
Classifier: Programming Language :: Python :: 3
Classifier: Programming Language :: Python :: 3.6
Classifier: Programming Language :: Python :: 3.7
Classifier: Programming Language :: Python :: 3.8
Classifier: Programming Language :: Python :: 3.9
Classifier: Programming Language :: Python :: 3.10
Classifier: License :: OSI Approved :: MIT License
Classifier: Operating System :: OS Independent
Classifier: Topic :: Internet :: Proxy Servers
Requires-Python: >=3.6
License-File: LICENSE
Requires-Dist: requests
